pandamonium/__init__.py
pandamonium/panda_kill_taskid.py
pandamonium/panda_resub_taskid.py
pandamonium/panda_shortname.py
pandamonium/pandamon.py
pandamonium/version.py
pandamonium/cli/__init__.py
pandamonium/cli/cli.py
pandamonium-0.3.1.dist-info/LICENSE
pandamonium-0.3.1.dist-info/METADATA
pandamonium-0.3.1.dist-info/WHEEL
pandamonium-0.3.1.dist-info/entry_points.txt
pandamonium-0.3.1.dist-info/top_level.txt
pandamonium-0.3.1.dist-info/RECORD
