Metadata-Version: 2.1
Name: pandamonium
Version: 0.3.1
Summary: Command line library to parse the Panda web API
Home-page: https://github.com/dguest/pandamonium
Author: Dan Guest, Matthew Feickert
Author-email: daniel.hay.guest@cern.ch, matthew.feickert@cern.ch
License: BSD 3-Clause
Project-URL: Documentation, https://dguest.github.io/pandamonium/
Project-URL: Source, https://github.com/dguest/pandamonium
Project-URL: Tracker, https://github.com/dguest/pandamonium/issues
Keywords: hep utilities physics panda
Classifier: Development Status :: 4 - Beta
Classifier: License :: OSI Approved :: BSD License
Classifier: Intended Audience :: Science/Research
Classifier: Topic :: Scientific/Engineering
Classifier: Topic :: Scientific/Engineering :: Physics
Classifier: Programming Language :: Python :: 2.7
Classifier: Programming Language :: Python :: 3
Classifier: Programming Language :: Python :: 3.6
Classifier: Programming Language :: Python :: 3.7
Classifier: Programming Language :: Python :: 3.8
Classifier: Programming Language :: Python :: 3.9
Classifier: Programming Language :: Python :: 3.10
Requires-Python: >=2.7
License-File: LICENSE
Requires-Dist: panda-client (>=1.4.82)
Provides-Extra: complete
Requires-Dist: black ; extra == 'complete'
Requires-Dist: bump2version (~=1.0) ; extra == 'complete'
Requires-Dist: check-manifest ; extra == 'complete'
Requires-Dist: isort (~=5.7) ; extra == 'complete'
Requires-Dist: pre-commit ; extra == 'complete'
Requires-Dist: pyflakes ; extra == 'complete'
Requires-Dist: pytest-console-scripts (~=0.2) ; extra == 'complete'
Requires-Dist: pytest-cov (~=2.8) ; extra == 'complete'
Requires-Dist: pytest-mock (~=3.0) ; extra == 'complete'
Requires-Dist: pytest (~=6.0) ; extra == 'complete'
Requires-Dist: twine ; extra == 'complete'
Provides-Extra: develop
Requires-Dist: black ; extra == 'develop'
Requires-Dist: bump2version (~=1.0) ; extra == 'develop'
Requires-Dist: check-manifest ; extra == 'develop'
Requires-Dist: isort (~=5.7) ; extra == 'develop'
Requires-Dist: pre-commit ; extra == 'develop'
Requires-Dist: pyflakes ; extra == 'develop'
Requires-Dist: pytest-console-scripts (~=0.2) ; extra == 'develop'
Requires-Dist: pytest-cov (~=2.8) ; extra == 'develop'
Requires-Dist: pytest-mock (~=3.0) ; extra == 'develop'
Requires-Dist: pytest (~=6.0) ; extra == 'develop'
Requires-Dist: twine ; extra == 'develop'
Provides-Extra: lint
Requires-Dist: black ; extra == 'lint'
Requires-Dist: isort (~=5.7) ; extra == 'lint'
Requires-Dist: pyflakes ; extra == 'lint'
Provides-Extra: test
Requires-Dist: pytest-console-scripts (~=0.2) ; extra == 'test'
Requires-Dist: pytest-cov (~=2.8) ; extra == 'test'
Requires-Dist: pytest-mock (~=3.0) ; extra == 'test'
Requires-Dist: pytest (~=6.0) ; extra == 'test'
